MANIFEST.in
README.md
requirements.txt
setup.py
version.txt
energon.egg-info/PKG-INFO
energon.egg-info/SOURCES.txt
energon.egg-info/dependency_links.txt
energon.egg-info/entry_points.txt
energon.egg-info/requires.txt
energon.egg-info/top_level.txt
energonai/__init__.py
energonai/batch_mgr.py
energonai/engine.py
energonai/pipe.py
energonai/task.py
energonai/worker.py
energonai/communication/__init__.py
energonai/communication/collective.py
energonai/communication/p2p.py
energonai/communication/ring.py
energonai/communication/utils.py
energonai/kernel/__init__.py
energonai/kernel/cuda_native/__init__.py
energonai/kernel/cuda_native/layer_norm.py
energonai/kernel/cuda_native/linear_func.py
energonai/kernel/cuda_native/one_layer_norm.py
energonai/kernel/cuda_native/scale_mask_softmax.py
energonai/kernel/cuda_native/transpose_pad.py
energonai/kernel/cuda_native/csrc/common.h
energonai/kernel/cuda_native/csrc/compat.h
energonai/kernel/cuda_native/csrc/get_ncclid.cpp
energonai/kernel/cuda_native/csrc/layer_norm_cuda.cpp
energonai/kernel/cuda_native/csrc/layer_norm_cuda_kernel.cu
energonai/kernel/cuda_native/csrc/linear_wrapper.cpp
energonai/kernel/cuda_native/csrc/one_layer_norm.cuh
energonai/kernel/cuda_native/csrc/one_layer_norm_cuda.cpp
energonai/kernel/cuda_native/csrc/one_layer_norm_cuda_kernel.cu
energonai/kernel/cuda_native/csrc/scale_mask_softmax_kernel.cu
energonai/kernel/cuda_native/csrc/scale_mask_softmax_wrapper.cpp
energonai/kernel/cuda_native/csrc/transpose_pad_fusion_kernel.cu
energonai/kernel/cuda_native/csrc/transpose_pad_fusion_wrapper.cpp
energonai/kernel/cuda_native/csrc/type_shim.h
energonai/legacy_batch_mgr/__init__.py
energonai/legacy_batch_mgr/dynamic_batch_manager.py
energonai/legacy_batch_mgr/naive_batch_manager.py
energonai/model/__init__.py
energonai/model/attention.py
energonai/model/downstream.py
energonai/model/embedding.py
energonai/model/endecoder.py
energonai/model/mlp.py
energonai/model/model_factory.py
energonai/nemesis/nemesis_manager.py
energonai/pipelinable/__init__.py
energonai/pipelinable/energon_tracer.py
energonai/pipelinable/split_method.py
energonai/pipelinable/split_policy.py
energonai/testing/__init__.py
